di_di_napalm_raisecom
