Metadata-Version: 2.1
Name: di-di-napalm-raisecom
Version: 0.11
Summary: functionality for raisecom devices, via netmiko connection for netbox
Home-page: UNKNOWN
Author: Ilya Gulin
License: Apache 2.0
Platform: UNKNOWN
